i8_ae/__init__.py
i8_ae/i8.py
i8.ae-2.0.0.dist-info/METADATA
i8.ae-2.0.0.dist-info/WHEEL
i8.ae-2.0.0.dist-info/top_level.txt
i8.ae-2.0.0.dist-info/RECORD
