Metadata-Version: 2.1
Name: i8.ae
Version: 2.0.0
Summary: i8.ae python library
Home-page: UNKNOWN
Author: ShahabCypher (Shahab Cypher)
Author-email: <shahabcypher@gmail.com>
License: UNKNOWN
Keywords: python,i8.ae,i8.ae Python,i8.ae api,python link shortener,py link shortener,py i8.ae,pypi i8,pypi i8.ae
Platform: UNKNOWN
Classifier: Development Status :: 5 - Production/Stable
Classifier: Intended Audience :: Developers
Classifier: Programming Language :: Python :: 3
Classifier: Operating System :: OS Independent
Requires-Dist: requests
